{
  "main": {
    "id": "2178b4b13ad8d220",
    "type": "split",
    "children": [
      {
        "id": "480113ca8d9c7463",
        "type": "tabs",
        "children": [
          {
            "id": "e857f13f3b3f005e",
            "type": "leaf",
            "pinned": true,
            "state": {
              "type": "markdown",
              "state": {
                "file": "🏠.md",
                "mode": "preview",
                "source": false,
                "backlinks": true,
                "backlinkOpts": {
                  "collapseAll": false,
                  "extraContext": false,
                  "sortOrder": "alphabetical",
                  "showSearch": false,
                  "searchQuery": "",
                  "backlinkCollapsed": false,
                  "unlinkedCollapsed": true
                }
              },
              "pinned": true,
              "icon": "lucide-file",
              "title": "🏠"
            }
          },
          {
            "id": "6cb800b274955341",
            "type": "leaf",
            "pinned": true,
            "state": {
              "type": "markdown",
              "state": {
                "file": "Comece Aqui 🎉.md",
                "mode": "preview",
                "source": false,
                "backlinks": false
              },
              "pinned": true,
              "icon": "lucide-file",
              "title": "Comece Aqui 🎉"
            }
          },
          {
            "id": "477e65d6599b8da9",
            "type": "leaf",
            "state": {
              "type": "markdown",
              "state": {
                "file": "Atlas/Maps/Data Science (Modelo).md",
                "mode": "preview",
                "source": false,
                "backlinks": false
              },
              "icon": "lucide-file",
              "title": "Data Science (Modelo)"
            }
          },
          {
            "id": "d724364d3f014487",
            "type": "leaf",
            "state": {
              "type": "markdown",
              "state": {
                "file": "README.md",
                "mode": "preview",
                "source": false,
                "backlinks": false
              },
              "icon": "lucide-file",
              "title": "README"
            }
          }
        ],
        "currentTab": 3
      }
    ],
    "direction": "vertical"
  },
  "left": {
    "id": "da223467db4c9158",
    "type": "split",
    "children": [
      {
        "id": "3ba83bbb7904c6a3",
        "type": "tabs",
        "children": [
          {
            "id": "b34c0f902b1265c0",
            "type": "leaf",
            "state": {
              "type": "file-explorer",
              "state": {
                "sortOrder": "alphabetical",
                "autoReveal": false
              },
              "icon": "lucide-folder-closed",
              "title": "Files"
            }
          },
          {
            "id": "c3dcb494a0674c29",
            "type": "leaf",
            "state": {
              "type": "search",
              "state": {
                "query": "",
                "matchingCase": false,
                "explainSearch": false,
                "collapseAll": false,
                "extraContext": false,
                "sortOrder": "alphabetical"
              },
              "icon": "lucide-search",
              "title": "Procurar"
            }
          },
          {
            "id": "e0f7509dece0369f",
            "type": "leaf",
            "state": {
              "type": "bookmarks",
              "state": {},
              "icon": "lucide-bookmark",
              "title": "Bookmarks"
            }
          },
          {
            "id": "f7119f2528338e15",
            "type": "leaf",
            "state": {
              "type": "outline",
              "state": {
                "file": "🏠.md",
                "followCursor": false,
                "showSearch": false,
                "searchQuery": ""
              },
              "icon": "lucide-list",
              "title": "Sumário de 🏠"
            }
          }
        ]
      },
      {
        "id": "5bf066390432bfba",
        "type": "tabs",
        "children": [
          {
            "id": "f8e7e9bde23996cf",
            "type": "leaf",
            "state": {
              "type": "localgraph",
              "state": {
                "file": "README.md",
                "options": {
                  "collapse-filter": false,
                  "search": "",
                  "localJumps": 1,
                  "localBacklinks": true,
                  "localForelinks": true,
                  "localInterlinks": false,
                  "showTags": false,
                  "showAttachments": false,
                  "hideUnresolved": false,
                  "collapse-color-groups": true,
                  "colorGroups": [],
                  "collapse-display": true,
                  "showArrow": false,
                  "textFadeMultiplier": 0,
                  "nodeSizeMultiplier": 1,
                  "lineSizeMultiplier": 1,
                  "collapse-forces": true,
                  "centerStrength": 0.518713248970312,
                  "repelStrength": 10,
                  "linkStrength": 1,
                  "linkDistance": 250,
                  "scale": 0.1846232765366677,
                  "close": true
                }
              },
              "icon": "lucide-git-fork",
              "title": "Graph of README"
            }
          },
          {
            "id": "80c8c0688f5d20e1",
            "type": "leaf",
            "state": {
              "type": "recent-files",
              "state": {},
              "icon": "clock",
              "title": "Recent Files"
            }
          }
        ],
        "currentTab": 1
      }
    ],
    "direction": "horizontal",
    "width": 401.5
  },
  "right": {
    "id": "3703f7d8eaeb01fd",
    "type": "split",
    "children": [
      {
        "id": "c4e9b6b7a7b97459",
        "type": "tabs",
        "dimension": 53.153153153153156,
        "children": [
          {
            "id": "72f1b9cde49a80fb",
            "type": "leaf",
            "state": {
              "type": "calendar",
              "state": {},
              "icon": "calendar-with-checkmark",
              "title": "Calendar"
            }
          },
          {
            "id": "d559413d9238a91f",
            "type": "leaf",
            "state": {
              "type": "tasknotes-pomodoro-view",
              "state": {},
              "icon": "clock",
              "title": "Pomodoro"
            }
          },
          {
            "id": "2386ef8588c3dc8e",
            "type": "leaf",
            "state": {
              "type": "tag",
              "state": {
                "sortOrder": "frequency",
                "useHierarchy": true,
                "showSearch": false,
                "searchQuery": ""
              },
              "icon": "lucide-tags",
              "title": "Tags"
            }
          },
          {
            "id": "1ebc49deb54dd0f7",
            "type": "leaf",
            "state": {
              "type": "all-properties",
              "state": {
                "sortOrder": "frequency",
                "showSearch": false,
                "searchQuery": ""
              },
              "icon": "lucide-archive",
              "title": "All properties"
            }
          },
          {
            "id": "40be355d2ebab86f",
            "type": "leaf",
            "state": {
              "type": "file-properties",
              "state": {
                "file": "README.md"
              },
              "icon": "lucide-info",
              "title": "File properties for README"
            }
          }
        ],
        "currentTab": 4
      },
      {
        "id": "3954ea8e597c4a31",
        "type": "tabs",
        "dimension": 46.846846846846844,
        "children": [
          {
            "id": "c133cbfbc6b00289",
            "type": "leaf",
            "state": {
              "type": "backlink",
              "state": {
                "file": "+/2025-10-15-new note.md",
                "collapseAll": false,
                "extraContext": false,
                "sortOrder": "alphabetical",
                "showSearch": false,
                "searchQuery": "",
                "backlinkCollapsed": false,
                "unlinkedCollapsed": true
              },
              "icon": "lucide-ghost",
              "title": "backlink"
            }
          },
          {
            "id": "7a2141420f060740",
            "type": "leaf",
            "state": {
              "type": "outgoing-link",
              "state": {
                "file": "System/Assets/_Atalhos.md",
                "linksCollapsed": false,
                "unlinkedCollapsed": true
              },
              "icon": "links-going-out",
              "title": "Outgoing links from _Atalhos"
            }
          },
          {
            "id": "143b5daa1b1727ea",
            "type": "leaf",
            "state": {
              "type": "markdown",
              "state": {
                "file": "System/Assets/_Atalhos.md",
                "mode": "preview",
                "source": false,
                "backlinks": true,
                "backlinkOpts": {
                  "collapseAll": false,
                  "extraContext": false,
                  "sortOrder": "alphabetical",
                  "showSearch": false,
                  "searchQuery": "",
                  "backlinkCollapsed": false,
                  "unlinkedCollapsed": true
                }
              },
              "icon": "lucide-file",
              "title": "_Atalhos"
            }
          }
        ],
        "currentTab": 2
      }
    ],
    "direction": "horizontal",
    "width": 354.5,
    "collapsed": true
  },
  "left-ribbon": {
    "hiddenItems": {
      "switcher:Open quick switcher": false,
      "graph:Open graph view": false,
      "canvas:Create new canvas": true,
      "daily-notes:Open today's daily note": false,
      "templates:Insert template": true,
      "command-palette:Open command palette": false,
      "random-note:Open random note": true,
      "workspaces:Manage workspace layouts": false,
      "bases:Create new base": true,
      "callout-manager:Insert Callout": false,
      "obsidian-kanban:Create new board": false,
      "periodic-notes:Open today": false,
      "templater-obsidian:Templater": false,
      "gridexplorer:Open grid view": false,
      "dashboard-navigator:Open dashboard navigator": false,
      "tasknotes:Open mini calendar": false,
      "tasknotes:Open advanced calendar": false,
      "tasknotes:Open task list": false,
      "tasknotes:Open notes": false,
      "tasknotes:Open agenda": false,
      "tasknotes:Open kanban board": false,
      "tasknotes:Open pomodoro": false,
      "tasknotes:Open pomodoro stats": false,
      "tasknotes:Create new task": false
    }
  },
  "active": "b34c0f902b1265c0",
  "lastOpenFiles": [
    "obsidian-starter-kit.zip",
    "Arquivo compactado.zip",
    "Arquivo compactado.zip.6xf1uh.part",
    "System/Templates/Snippet/@ 2 tabs.md",
    "System/Templates/Snippet/_ tp -templater clipboard.md",
    "System/Templates/Snippet/_-img-link.md",
    "System/Templates/Snippet/_ tp input templater.md",
    "System/Templates/Snippet/_ tp jump cursor.md",
    "System/Templates/_-TODAY.md",
    "System/Templates/-LINK-TODAY.md",
    "Projects & Areas/Projects/Ongoing/Projeto Modelo/Projeto Modelo.md",
    "Projects & Areas/Areas/Desenvolvimento Pessoal/Desenvolvimento Pessoal.md",
    "Calendar & Review/Daily Notes/2025-10-06.md",
    "Atlas/Maps/Habits Map (Modelo).md",
    "🏠.md",
    "Atlas/Maps/Data Science (Modelo).md",
    "Atlas/Maps/Dashboard++ (Modelo).md",
    "Atlas/Maps/++ Gestão de Conhecimento.md",
    "Atlas/Maps/+ Gestão de Conhecimento.md",
    "Atlas/Conceitos/ACE & ARC Frameworks/+ ACE Pack.md",
    "Atlas/Conceitos/ACE & ARC Frameworks/How the Areas folder works.md",
    "Atlas/Conceitos/ACE & ARC Frameworks/How the Dots folder works.md",
    "Atlas/Dots",
    "Atlas/Conceitos/ACE & ARC Frameworks/How folder System Works.md",
    "Atlas/Conceitos/ACE & ARC Frameworks/How Calendar works.md",
    "Atlas/Conceitos/ACE & ARC Frameworks/How Atlas works.md",
    "Atlas/Conceitos/ACE & ARC Frameworks/How + works.md",
    "Atlas/Conceitos/ACE & ARC Frameworks/Comunicar.md",
    "Atlas/Conceitos/ACE & ARC Frameworks/Adicionar.md",
    "Calendar & Review.zip",
    "Projects & Areas/Projects/Ongoing/Projeto modelo",
    "Projects & Areas/Projects/Ongoing",
    "Projects & Areas.zip",
    "Projects & Areas/Projects/Ongoing/Projeto Modelo",
    "Atlas/Maps",
    "Atlas/Conceitos",
    "System/Media/Media/banners/navigation-7320887_1920.jpg",
    "System/Media/Media/banners/hands-1373363_1920.jpg",
    "System/Media/Media/banners/computer-820281.jpg",
    "System/Media/Media/banners/sunrise-8290940_1920.jpg",
    "System/Media/Media/banners/smile-5128742_1920.jpg",
    "System/Media/banner pos.png",
    "System/Media/bb.png",
    "System/Media/wall2.png",
    "System/Media/wall.png",
    "System/Media/Pasted image 20251009183318.png",
    "Sem título.canvas",
    "30 Knowlegde/34 Maps &  Index/34.2 Maps/+_CANVAS_AOC.canvas",
    "30 Knowlegde/34 Maps &  Index/34.2 Maps/mapa-pkm.canvas",
    "30 Knowlegde/34 Maps &  Index/34.2 Maps/+_CANVAS_AOC 1.canvas",
    "30 Knowlegde/34 Maps &  Index/34.2 Maps/+_CANVAS-MENTORIA.CARLOS.canvas",
    "30 Knowlegde/34 Maps &  Index/34.2 Maps/+_CANVAS-Fluxograma-de-decisoes-de-anuncios.canvas",
    "30 Knowlegde/34 Maps &  Index/34.2 Maps/+_CANVAS-DATASCIENCE.canvas",
    "30 Knowlegde/34.2 Maps/mapa-pkm.canvas",
    "30 Knowlegde/34.2 Maps/+_CANVAS_AOC.canvas",
    "30 Knowlegde/34.2 Maps/+_CANVAS_AOC 1.canvas"
  ]
}